linkfire
