Metadata-Version: 1.0
Name: python-linkfire
Version: 0.2
Summary: Python linkfire.com API
Home-page: https://github.com/koalalorenzo/python-linkfire
Author: Lorenzo Setale ( http://who.is.lorenzo.setale.me/? )
Author-email: koalalorenzo@gmail.com
License: UNKNOWN
Platform: UNKNOWN
